piper/__init__.py
piper/__main__.py
piper/config.py
piper/const.py
piper/download.py
piper/file_hash.py
piper/http_server.py
piper/util.py
piper/voice.py
piper/voices.json
tests/__init__.py
tests/conftest.py
tests/test_runtime.py
tests/test_util_impl.py
piper_tts_plus-20250711.64548.dist-info/METADATA
piper_tts_plus-20250711.64548.dist-info/WHEEL
piper_tts_plus-20250711.64548.dist-info/entry_points.txt
piper_tts_plus-20250711.64548.dist-info/top_level.txt
piper_tts_plus-20250711.64548.dist-info/RECORD
